modules/__init__.py
modules/cross_over_controller.py
modules/latency_module.py
modules/volume_analyser.py
pythonAPI/__init__.py
pythonAPI/runnbboquote.py
pythonAPI/security_credentials.py
latency-0.1.0.dist-info/METADATA
latency-0.1.0.dist-info/WHEEL
latency-0.1.0.dist-info/top_level.txt
latency-0.1.0.dist-info/RECORD
