Metadata-Version: 2.1
Name: latency
Version: 0.1.0
Summary: Library for latency simulation and query for Onetick
Home-page: https://gitlab.awsged.com/bigdata/onetick_latency.git
Author: Alexandre Levert
Author-email: alexandre.levert.1@bnc.ca
License: UNKNOWN
Platform: UNKNOWN
Classifier: Development Status :: 3 - Alpha
Classifier: Intended Audience :: Developers
Classifier: Programming Language :: Python :: 3
Classifier: Operating System :: OS Independent
Requires-Python: >=3.9
Requires-Dist: matplotlib
Requires-Dist: numpy
Requires-Dist: pandas
Requires-Dist: pytz
